{
  "model_path": "/Volumes/emberstuff/xLSTM/xlstm_7b_model",
  "prompt_file": "prompt_16k.txt",
  "new": 32,
  "backend": "queued",
  "mode": "random",
  "trials": 16,
  "repeats": 1,
  "heads_min": 2,
  "heads_max": 8,
  "chunks_min": 16,
  "chunks_max": 64,
  "workers_min": 4,
  "workers_max": 8,
  "log_dir": "runs/mps_opt",
  "tag": "queued16k",
  "outputs_dir": "runs/mps_opt/outputs",
  "chunkwise_backend": "queued_compiled_steps",
  "workers": 6,
  "heads_per_band": 4,
  "streams": 0,
  "chunk_size": 32
}

